hyprwindow/__init__.py
hyprwindow/config.py
hyprwindow-0.1.3.dist-info/METADATA
hyprwindow-0.1.3.dist-info/WHEEL
hyprwindow-0.1.3.dist-info/entry_points.txt
hyprwindow-0.1.3.dist-info/licenses/LICENSE
hyprwindow-0.1.3.dist-info/RECORD
